raven/cli.py
raven/git.py
raven/commands/awaken.py
raven/commands/fly.py
raven/commands/gather.py
raven/commands/huginn.py
raven/commands/mark.py
raven/commands/merge.py
raven/commands/muninn.py
raven/commands/paths.py
raven/commands/perch.py
raven/commands/spawn.py
raven/commands/sync.py
raven/commands/watch.py
odin_raven-0.1.0.dist-info/METADATA
odin_raven-0.1.0.dist-info/WHEEL
odin_raven-0.1.0.dist-info/entry_points.txt
odin_raven-0.1.0.dist-info/top_level.txt
odin_raven-0.1.0.dist-info/RECORD
