Metadata-Version: 2.4
Name: odin-raven
Version: 0.1.0
Summary: Be Odin. Send ravens. A semantic CLI wrapper around Git.
Author-email: Sajeed <sajeed725333@gmail.com>
Requires-Python: >=3.10
Requires-Dist: click
